odoo/addons/project_group_hr_timesheet/README.rst
odoo/addons/project_group_hr_timesheet/__init__.py
odoo/addons/project_group_hr_timesheet/__manifest__.py
odoo/addons/project_group_hr_timesheet/i18n/it.po
odoo/addons/project_group_hr_timesheet/i18n/project_group_hr_timesheet.pot
odoo/addons/project_group_hr_timesheet/readme/CONTRIBUTORS.md
odoo/addons/project_group_hr_timesheet/readme/DESCRIPTION.md
odoo/addons/project_group_hr_timesheet/security/security.xml
odoo/addons/project_group_hr_timesheet/static/description/icon.png
odoo/addons/project_group_hr_timesheet/static/description/index.html
odoo_addon_project_group_hr_timesheet-17.0.1.0.0.3.dist-info/METADATA
odoo_addon_project_group_hr_timesheet-17.0.1.0.0.3.dist-info/WHEEL
odoo_addon_project_group_hr_timesheet-17.0.1.0.0.3.dist-info/top_level.txt
odoo_addon_project_group_hr_timesheet-17.0.1.0.0.3.dist-info/RECORD
